README.md
setup.py
x_menu.egg-info/PKG-INFO
x_menu.egg-info/SOURCES.txt
x_menu.egg-info/dependency_links.txt
x_menu.egg-info/entry_points.txt
x_menu.egg-info/not-zip-safe
x_menu.egg-info/requires.txt
x_menu.egg-info/top_level.txt
x_menu_src/__init__.py
x_menu_src/charactors.py
x_menu_src/cmd.py
x_menu_src/event.py
x_menu_src/example.py
x_menu_src/example2.py
x_menu_src/example3.py
x_menu_src/log.py
x_menu_src/map.py
x_menu_src/menu.py
x_menu_src/text.py
x_menu_src/tree.py