Metadata-Version: 1.0
Name: x-menu
Version: 0.0.6
Summary: api for console ui
Home-page: https://github.com/Qingluan/console-ui.git
Author: auth
Author-email: darkhackdevil@gmail.com
License: MIT
Platform: UNKNOWN
